{
  "id": "2198880005949722040",
  "type": 0,
  "content": "uvlqbna",
  "channel_id": "6499973936928851736",
  "author": {
    "id": "984314203649111293",
    "username": "7933241900576644",
    "display_name": null,
    "avatar": "eae5905ad2d18d7c8deca20478b088b5",
    "avatar_decoration": null,
    "discriminator": "1493",
    "public_flags": 4194560
  },
  "attachments": [],
  "embeds": [],
  "mentions": [],
  "mention_roles": [],
  "pinned": false,
  "mention_everyone": false,
  "tts": false,
  "timestamp": "2023-02-14T00:45:50.055Z",
  "edited_timestamp": null,
  "flags": 0,
  "components": []
}